{
    "data": {
        "tournament_matches": {
            "matches": [
                {
                    "match_id": 4583998011
                },
                {
                    "match_id": 4583992900
                },
                {
                    "match_id": 4583990277
                },
                {
                    "match_id": 4583971219
                },
                {
                    "match_id": 4583872244
                },
                {
                    "match_id": 4583865551
                },
                {
                    "match_id": 4583699904
                },
                {
                    "match_id": 4583692247
                },
                {
                    "match_id": 4583611843
                },
                {
                    "match_id": 4583581680
                },
                {
                    "match_id": 4583541550
                },
                {
                    "match_id": 4583530543
                },
                {
                    "match_id": 4583529539
                },
                {
                    "match_id": 4583527633
                },
                {
                    "match_id": 4583351795
                },
                {
                    "match_id": 4583330794
                },
                {
                    "match_id": 4583329981
                },
                {
                    "match_id": 4583324948
                },
                {
                    "match_id": 4583304724
                },
                {
                    "match_id": 4583276337
                },
                {
                    "match_id": 4583129864
                },
                {
                    "match_id": 4583114920
                },
                {
                    "match_id": 4583075887
                },
                {
                    "match_id": 4583057643
                },
                {
                    "match_id": 4582913393
                },
                {
                    "match_id": 4582902817
                },
                {
                    "match_id": 4582900498
                },
                {
                    "match_id": 4582890604
                }
            ]
        }
    }
}