{
    "data": {
        "tournament_matches": {
            "matches": [
                {
                    "match_id": 5932310570
                },
                {
                    "match_id": 5932235516
                },
                {
                    "match_id": 5932107807
                },
                {
                    "match_id": 5932036681
                },
                {
                    "match_id": 5931984407
                },
                {
                    "match_id": 5931970757
                },
                {
                    "match_id": 5931915438
                },
                {
                    "match_id": 5931911761
                },
                {
                    "match_id": 5931847123
                },
                {
                    "match_id": 5931786049
                },
                {
                    "match_id": 5931777676
                },
                {
                    "match_id": 5931722231
                },
                {
                    "match_id": 5931720954
                },
                {
                    "match_id": 5930303167
                },
                {
                    "match_id": 5930301041
                },
                {
                    "match_id": 5930256378
                },
                {
                    "match_id": 5930233375
                },
                {
                    "match_id": 5930226047
                },
                {
                    "match_id": 5930216748
                },
                {
                    "match_id": 5930207603
                },
                {
                    "match_id": 5930171186
                },
                {
                    "match_id": 5930165522
                },
                {
                    "match_id": 5930154602
                },
                {
                    "match_id": 5930151916
                },
                {
                    "match_id": 5930149088
                },
                {
                    "match_id": 5930094648
                },
                {
                    "match_id": 5930088391
                },
                {
                    "match_id": 5930088042
                },
                {
                    "match_id": 5930086248
                },
                {
                    "match_id": 5930085258
                },
                {
                    "match_id": 5930080836
                },
                {
                    "match_id": 5930074519
                },
                {
                    "match_id": 5930032972
                },
                {
                    "match_id": 5930027854
                }
            ]
        }
    }
}