{
    "data": {
        "tournament_matches": {
            "matches": [
                {
                    "match_id": 5926851979
                },
                {
                    "match_id": 5926732118
                },
                {
                    "match_id": 5926596132
                },
                {
                    "match_id": 5926498037
                },
                {
                    "match_id": 5926402991
                },
                {
                    "match_id": 5926212113
                },
                {
                    "match_id": 5926148072
                },
                {
                    "match_id": 5926065815
                },
                {
                    "match_id": 5925119996
                },
                {
                    "match_id": 5924956181
                },
                {
                    "match_id": 5924812056
                },
                {
                    "match_id": 5924712320
                },
                {
                    "match_id": 5924610089
                },
                {
                    "match_id": 5924507520
                },
                {
                    "match_id": 5924430391
                },
                {
                    "match_id": 5924343990
                },
                {
                    "match_id": 5924231037
                },
                {
                    "match_id": 5924160626
                },
                {
                    "match_id": 5924068428
                },
                {
                    "match_id": 5922871615
                },
                {
                    "match_id": 5922768273
                },
                {
                    "match_id": 5922679457
                },
                {
                    "match_id": 5922602670
                },
                {
                    "match_id": 5922512609
                },
                {
                    "match_id": 5922438740
                },
                {
                    "match_id": 5922379061
                },
                {
                    "match_id": 5922293044
                },
                {
                    "match_id": 5922226336
                },
                {
                    "match_id": 5922162182
                },
                {
                    "match_id": 5921084683
                },
                {
                    "match_id": 5920993291
                },
                {
                    "match_id": 5920889352
                },
                {
                    "match_id": 5920806694
                },
                {
                    "match_id": 5920714068
                },
                {
                    "match_id": 5920638214
                },
                {
                    "match_id": 5920564188
                },
                {
                    "match_id": 5920494710
                },
                {
                    "match_id": 5920449253
                },
                {
                    "match_id": 5920377449
                },
                {
                    "match_id": 5919422016
                },
                {
                    "match_id": 5919286556
                },
                {
                    "match_id": 5919165162
                },
                {
                    "match_id": 5919074158
                },
                {
                    "match_id": 5918982217
                },
                {
                    "match_id": 5918906877
                },
                {
                    "match_id": 5918832729
                },
                {
                    "match_id": 5918743805
                },
                {
                    "match_id": 5918691827
                },
                {
                    "match_id": 5917514439
                },
                {
                    "match_id": 5917443590
                }
            ]
        }
    }
}